search_engine_tool/__init__.py
search_engine_tool/search_engine_tool.py
search_engine_tool/engine/__init__.py
search_engine_tool/engine/bing.py
search_engine_tool/engine/google.py
search_engine_tool/engine/yahoo.py
search_engine_tool-0.3.0.dist-info/LICENSE
search_engine_tool-0.3.0.dist-info/METADATA
search_engine_tool-0.3.0.dist-info/WHEEL
search_engine_tool-0.3.0.dist-info/top_level.txt
search_engine_tool-0.3.0.dist-info/RECORD
