Metadata-Version: 2.1
Name: search-engine-tool
Version: 0.3.0
Summary: 搜索引擎API Bing / Google / Yahoo / Baidu / Sogou / 360 
Home-page: https://github.com/freewu/search-engine-tool
Author: bluefrog
Author-email: bluefrog.wu@gmail.com
License: MIT
Classifier: Development Status :: 3 - Alpha
Classifier: Intended Audience :: Developers
Classifier: License :: OSI Approved :: MIT License
Classifier: Programming Language :: Python
Classifier: Programming Language :: Python :: 3
Classifier: Programming Language :: Python :: 3.11
License-File: LICENSE
Requires-Dist: selenium
